revisitpy/StudyConfigSchema.json
revisitpy/__init__.py
revisitpy/models.py
revisitpy/revisitpy.py
revisitpy/widget.py
revisitpy/static/widget.css
revisitpy/static/widget.js
revisitpy-2.3.1.dist-info/METADATA
revisitpy-2.3.1.dist-info/WHEEL
revisitpy-2.3.1.dist-info/licenses/LICENSE
revisitpy-2.3.1.dist-info/RECORD
