Metadata-Version: 2.4
Name: revisitpy
Version: 2.3.1
License-File: LICENSE
Requires-Dist: anywidget
Requires-Dist: pandas
Requires-Dist: pydantic>=2.10.5
Provides-Extra: dev
Requires-Dist: jupyterlab; extra == 'dev'
Requires-Dist: watchfiles; extra == 'dev'
